eloqent/__init__.py
eloqent/__main__.py
eloqent/main.py
eloqent/cli/__init__.py
eloqent/cli/commands.py
eloqent/engine/__init__.py
eloqent/engine/actions.py
eloqent/engine/constants.py
eloqent/engine/context.py
eloqent/engine/manager.py
eloqent/engine/planner.py
eloqent/utils/__init__.py
eloqent/utils/helpers.py
eloqent/utils/loaders.py
eloqent-0.1.0.dist-info/METADATA
eloqent-0.1.0.dist-info/WHEEL
eloqent-0.1.0.dist-info/entry_points.txt
eloqent-0.1.0.dist-info/RECORD
