Metadata-Version: 2.3
Name: eloqent
Version: 0.1.0
Summary: Nest is a tool to help you build your own AI assistant
Requires-Python: >=3.11
Requires-Dist: dspy-ai>=2.4.14
Requires-Dist: pypred>=0.4.0
Requires-Dist: rich>=13.8.1
Requires-Dist: typer>=0.12.5
